bitfloat/__init__.py
bitfloat/__main__.py
bitfloat-0.1.1.dist-info/licenses/LICENSE
bitfloat-0.1.1.dist-info/METADATA
bitfloat-0.1.1.dist-info/WHEEL
bitfloat-0.1.1.dist-info/entry_points.txt
bitfloat-0.1.1.dist-info/top_level.txt
bitfloat-0.1.1.dist-info/RECORD
