Metadata-Version: 2.4
Name: bitfloat
Version: 0.1.1
Summary: IEEE 754 floating-point arithmetic with arbitrary precision
Author-email: sjjeong94 <sjjeong94@gmail.com>
License: MIT License
Project-URL: Homepage, https://github.com/sjjeong94/bitfloat
Project-URL: Repository, https://github.com/sjjeong94/bitfloat
Classifier: Programming Language :: Python :: 3
Classifier: License :: OSI Approved :: MIT License
Classifier: Operating System :: OS Independent
Requires-Python: >=3.8
License-File: LICENSE
Provides-Extra: dev
Requires-Dist: pytest>=7.0; extra == "dev"
Dynamic: license-file
